<Root>
  <nodo name_node="dwf_head_cockpit" schematic_pos="[1500,200]" />
  <nodo name_node="dwf_centre_torso" schematic_pos="[1500,500]" />
  <nodo name_node="dwf_left_torso" schematic_pos="[1700,500]" />
  <nodo name_node="dwf_right_torso" schematic_pos="[1300,500]" />
  
  <nodo name_node="dwf_left_arm_clavicle" schematic_pos="[1830,150]" />
  <nodo name_node="dwf_left_arm_upperarm" schematic_pos="[2030,220]" />
  <nodo name_node="dwf_left_arm_forearm" schematic_pos="[2230,290]" />
  <nodo name_node="dwf_left_arm_forearm_hand" schematic_pos="[2430,360]" />
  
  <nodo name_node="dwf_right_arm_clavicle" schematic_pos="[1170,150]" />
  <nodo name_node="dwf_right_arm_upperarm" schematic_pos="[970,220]" />
  <nodo name_node="dwf_right_arm_forearm" schematic_pos="[770,290]" />
  <nodo name_node="dwf_right_arm_forearm_hand" schematic_pos="[570,360]" />
  
  <nodo name_node="dwf_centre_torso_rear" schematic_pos="[1500,300]" />
  <nodo name_node="dwf_left_torso_rear" schematic_pos="[1700,300]" />
  <nodo name_node="dwf_right_torso_rear" schematic_pos="[1300,300]" />
  <nodo name_node="dwf_centre_torso_twist" schematic_pos="[1500,1330]" />
  <nodo name_node="dwf_centre_torso_pelvis" schematic_pos="[1500,1570]" />
  <nodo name_node="dwf_right_leg_hip" schematic_pos="[1350,1530]" />
  <nodo name_node="dwf_left_leg_hip" schematic_pos="[1650,1530]" />
  <nodo name_node="dwf_left_leg_thigh" schematic_pos="[1750,1630]" />
  <nodo name_node="dwf_right_leg_thigh" schematic_pos="[1250,1630]" />
  <nodo name_node="dwf_centre_torso_pelvis_rear" schematic_pos="[1500,1450]" />
  <nodo name_node="dwf_right_leg_calf" schematic_pos="[1150,1730]" />
  <nodo name_node="dwf_left_leg_calf" schematic_pos="[1850,1730]" />
  
  
  
  <nodo name_node="dwf_left_leg_foot" schematic_pos="[1970,1830]" />
  <nodo name_node="dwf_left_leg_toe0" schematic_pos="[2090,2020]" />
  <nodo name_node="dwf_left_leg_toe1" schematic_pos="[2210,2020]" />
  <nodo name_node="dwf_left_leg_pinky1" schematic_pos="[1970,1950]" />  
  <nodo name_node="dwf_left_leg_index1" schematic_pos="[1970,2090]" /> 
  <nodo name_node="dwf_left_leg_talon_pinky0" schematic_pos="[1850,1950]" />  
  <nodo name_node="dwf_left_leg_talon0" schematic_pos="[1850,2090]" />
  <nodo name_node="dwf_left_leg_talon_pinky1" schematic_pos="[1730,1950]" />  
  <nodo name_node="dwf_left_leg_talon1" schematic_pos="[1730,2090]" /> 
  
  <nodo name_node="dwf_right_leg_foot" schematic_pos="[1050,1830]" />
  <nodo name_node="dwf_right_leg_toe0" schematic_pos="[930,2020]" />
  <nodo name_node="dwf_right_leg_toe1" schematic_pos="[810,2020]" />
  <nodo name_node="dwf_right_leg_pinky1" schematic_pos="[1050,1950]" />  
  <nodo name_node="dwf_right_leg_index1" schematic_pos="[1050,2090]" /> 
  <nodo name_node="dwf_right_leg_talon_pinky0" schematic_pos="[1170,1950]" />  
  <nodo name_node="dwf_right_leg_talon0" schematic_pos="[1170,2090]" />
  <nodo name_node="dwf_right_leg_talon_pinky1" schematic_pos="[1290,1950]" />  
  <nodo name_node="dwf_right_leg_talon1" schematic_pos="[1290,2090]" /> 
  

  
  
  <nodo name_node="dwf_left_arm_clavicle_damaged" schematic_pos="[1830,-290]" />
  <nodo name_node="dwf_left_arm_upperarm_damaged" schematic_pos="[2030,-220]" />
  <nodo name_node="dwf_left_arm_forearm_damaged" schematic_pos="[2230,-150]" />
  <nodo name_node="dwf_left_arm_forearm_hand_damaged" schematic_pos="[2430,-080]" />
  <nodo name_node="dwf_right_arm_clavicle_damaged" schematic_pos="[1170,-290]" />
  <nodo name_node="dwf_right_arm_upperarm_damaged" schematic_pos="[970,-220]" />
  <nodo name_node="dwf_right_arm_forearm_damaged" schematic_pos="[770,-150]" />
  <nodo name_node="dwf_right_arm_forearm_hand_damaged" schematic_pos="[570,-080]" />
  


  
  
  
  
  

   

 

  
  



  <nodo name_node="dwf_left_leg_calf_hero" schematic_pos="[2100,1730]" />
  <nodo name_node="dwf_right_leg_calf_hero" schematic_pos="[880,1730]" />
  <nodo name_node="dwf_left_arm_upperarm_hero" schematic_pos="[2030,100]" />
  <nodo name_node="dwf_right_arm_upperarm_hero" schematic_pos="[970,100]" />
  
  
  <nodo name_node="dwf_head_cockpit_ams_ah1" schematic_pos="[1450,-450]" />
  <nodo name_node="dwf_head_cockpit_lams_ah1" schematic_pos="[1550,-450]" />
  
  <nodo name_node="dwf_head_cockpit_hppc_eh1" schematic_pos="[1050,-580]" />
  <nodo name_node="dwf_head_cockpit_ppc_eh1" schematic_pos="[1150,-580]" />  
  <nodo name_node="dwf_head_cockpit_snppc_eh1" schematic_pos="[1250,-580]" />
  <nodo name_node="dwf_head_cockpit_lppc_eh1" schematic_pos="[1350,-580]" />
  <nodo name_node="dwf_head_cockpit_laser_eh1" schematic_pos="[1450,-580]" />
  <nodo name_node="dwf_head_cockpit_flamer_eh1" schematic_pos="[1550,-580]" />
  <nodo name_node="dwf_head_cockpit_hppc_eh2" schematic_pos="[1050,-710]" />
  <nodo name_node="dwf_head_cockpit_ppc_eh2" schematic_pos="[1150,-710]" />  
  <nodo name_node="dwf_head_cockpit_snppc_eh2" schematic_pos="[1250,-710]" />
  <nodo name_node="dwf_head_cockpit_lppc_eh2" schematic_pos="[1350,-710]" />
  <nodo name_node="dwf_head_cockpit_laser_eh2" schematic_pos="[1450,-710]" />
  <nodo name_node="dwf_head_cockpit_flamer_eh2" schematic_pos="[1550,-710]" />
  
  

  
  
  <nodo name_node="dwf_centre_torso_ams_ah1" schematic_pos="[1450,650]" />
  <nodo name_node="dwf_centre_torso_lams_ah1" schematic_pos="[1550,650]" />
  
  <nodo name_node="dwf_centre_torso_hppc_eh1" schematic_pos="[1050,780]" />
  <nodo name_node="dwf_centre_torso_ppc_eh1" schematic_pos="[1150,780]" />
  <nodo name_node="dwf_centre_torso_snppc_eh1" schematic_pos="[1250,780]" />
  <nodo name_node="dwf_centre_torso_lppc_eh1" schematic_pos="[1350,780]" />
  <nodo name_node="dwf_centre_torso_laser_eh1" schematic_pos="[1450,780]" />
  <nodo name_node="dwf_centre_torso_flamer_eh1" schematic_pos="[1550,780]" />

  <nodo name_node="dwf_centre_torso_hppc_eh2" schematic_pos="[1050,910]" />
  <nodo name_node="dwf_centre_torso_ppc_eh2" schematic_pos="[1150,910]" />
  <nodo name_node="dwf_centre_torso_snppc_eh2" schematic_pos="[1250,910]" />
  <nodo name_node="dwf_centre_torso_lppc_eh2" schematic_pos="[1350,910]" />
  <nodo name_node="dwf_centre_torso_laser_eh2" schematic_pos="[1450,910]" />
  <nodo name_node="dwf_centre_torso_flamer_eh2" schematic_pos="[1550,910]" />
  
  
  <nodo name_node="dwf_centre_torso_narc_mh1" schematic_pos="[1050,1040]" />
  <nodo name_node="dwf_centre_torso_missile2_mh1" schematic_pos="[1150,1040]" />
  <nodo name_node="dwf_centre_torso_missile3_mh1" schematic_pos="[1250,1040]" />
  <nodo name_node="dwf_centre_torso_missile4_mh1" schematic_pos="[1350,1040]" />
  <nodo name_node="dwf_centre_torso_missile5_mh1" schematic_pos="[1450,1040]" />
  <nodo name_node="dwf_centre_torso_missile6_mh1" schematic_pos="[1550,1040]" />
  <nodo name_node="dwf_centre_torso_missile9_mh1" schematic_pos="[1650,1040]" />
  <nodo name_node="dwf_centre_torso_missile10_mh1" schematic_pos="[1750,1040]" />
  <nodo name_node="dwf_centre_torso_missile12_mh1" schematic_pos="[1850,1040]" />  
  <nodo name_node="dwf_centre_torso_missile15_mh1" schematic_pos="[1950,1040]" />
  <nodo name_node="dwf_centre_torso_missile20_mh1" schematic_pos="[2050,1040]" />


  
  
  
  
  
  
  
  

  <nodo name_node="dwf_left_torso_ams_ah1" schematic_pos="[2760,000]" />
  <nodo name_node="dwf_left_torso_lams_ah1" schematic_pos="[2860,000]" />
  <nodo name_node="dwf_left_torso_ams_ah2" schematic_pos="[2760,-150]" />
  <nodo name_node="dwf_left_torso_lams_ah2" schematic_pos="[2860,-150]" />    
  
  <nodo name_node="dwf_left_torso_hppc_eh1" schematic_pos="[3260,150]" />
  <nodo name_node="dwf_left_torso_ppc_eh1" schematic_pos="[3160,150]" />  
  <nodo name_node="dwf_left_torso_snppc_eh1" schematic_pos="[3060,150]" />
  <nodo name_node="dwf_left_torso_lppc_eh1" schematic_pos="[2960,150]" />
  <nodo name_node="dwf_left_torso_laser_eh1" schematic_pos="[2860,150]" />
  <nodo name_node="dwf_left_torso_flamer_eh1" schematic_pos="[2760,150]" />
  <nodo name_node="dwf_left_torso_hppc_eh2" schematic_pos="[3260,280]" />
  <nodo name_node="dwf_left_torso_ppc_eh2" schematic_pos="[3160,280]" />  
  <nodo name_node="dwf_left_torso_snppc_eh2" schematic_pos="[3060,280]" />
  <nodo name_node="dwf_left_torso_lppc_eh2" schematic_pos="[2960,280]" />
  <nodo name_node="dwf_left_torso_laser_eh2" schematic_pos="[2860,280]" />
  <nodo name_node="dwf_left_torso_flamer_eh2" schematic_pos="[2760,280]" />
  <nodo name_node="dwf_left_torso_hppc_eh3" schematic_pos="[3260,-280]" />
  <nodo name_node="dwf_left_torso_ppc_eh3" schematic_pos="[3160,-280]" />  
  <nodo name_node="dwf_left_torso_snppc_eh3" schematic_pos="[3060,-280]" />
  <nodo name_node="dwf_left_torso_lppc_eh3" schematic_pos="[2960,-280]" />
  <nodo name_node="dwf_left_torso_laser_eh3" schematic_pos="[2860,-280]" />
  <nodo name_node="dwf_left_torso_flamer_eh3" schematic_pos="[2760,-280]" />
  <nodo name_node="dwf_left_torso_hppc_eh4" schematic_pos="[3260,-410]" />
  <nodo name_node="dwf_left_torso_ppc_eh4" schematic_pos="[3160,-410]" />  
  <nodo name_node="dwf_left_torso_snppc_eh4" schematic_pos="[3060,-410]" />
  <nodo name_node="dwf_left_torso_lppc_eh4" schematic_pos="[2960,-410]" />
  <nodo name_node="dwf_left_torso_laser_eh4" schematic_pos="[2860,-410]" />
  <nodo name_node="dwf_left_torso_flamer_eh4" schematic_pos="[2760,-410]" />
  <nodo name_node="dwf_left_torso_hppc_eh5" schematic_pos="[3260,-540]" />
  <nodo name_node="dwf_left_torso_ppc_eh5" schematic_pos="[3160,-540]" />  
  <nodo name_node="dwf_left_torso_snppc_eh5" schematic_pos="[3060,-540]" />
  <nodo name_node="dwf_left_torso_lppc_eh5" schematic_pos="[2960,-540]" />
  <nodo name_node="dwf_left_torso_laser_eh5" schematic_pos="[2860,-540]" />
  <nodo name_node="dwf_left_torso_flamer_eh5" schematic_pos="[2760,-540]" />
  
  <nodo name_node="dwf_left_torso_lmg_bh1" schematic_pos="[2760,420]" />
  <nodo name_node="dwf_left_torso_mg_bh1" schematic_pos="[2860,420]" />
  <nodo name_node="dwf_left_torso_hmg_bh1" schematic_pos="[2960,420]" />
  <nodo name_node="dwf_left_torso_ac2_bh1" schematic_pos="[3060,420]" />
  <nodo name_node="dwf_left_torso_uac2_bh1" schematic_pos="[3160,420]" />  
  <nodo name_node="dwf_left_torso_rac2_bh1" schematic_pos="[3260,420]" />
  <nodo name_node="dwf_left_torso_lbx2_bh1" schematic_pos="[3360,420]" />  
  <nodo name_node="dwf_left_torso_ac5_bh1" schematic_pos="[3460,420]" />
  <nodo name_node="dwf_left_torso_lbx5_bh1" schematic_pos="[3560,420]" />
  <nodo name_node="dwf_left_torso_uac5_bh1" schematic_pos="[3660,420]" />
  <nodo name_node="dwf_left_torso_lgauss_bh1" schematic_pos="[3760,420]" />
  <nodo name_node="dwf_left_torso_rac5_bh1" schematic_pos="[3860,420]" />
  <nodo name_node="dwf_left_torso_lbx10_bh1" schematic_pos="[3960,420]" />
  <nodo name_node="dwf_left_torso_ac10_bh1" schematic_pos="[4060,420]" />
  <nodo name_node="dwf_left_torso_uac10_bh1" schematic_pos="[4160,420]" />
  <nodo name_node="dwf_left_torso_gauss_bh1" schematic_pos="[4260,420]" />
  <nodo name_node="dwf_left_torso_ac20_bh1" schematic_pos="[4360,420]" />
  <nodo name_node="dwf_left_torso_uac20_bh1" schematic_pos="[4460,420]" />
  <nodo name_node="dwf_left_torso_lbx20_bh1" schematic_pos="[4560,420]" />
  <nodo name_node="dwf_left_torso_hgauss_bh1" schematic_pos="[4660,420]" />
  <nodo name_node="dwf_left_torso_lmg_bh2" schematic_pos="[2760,590]" />
  <nodo name_node="dwf_left_torso_mg_bh2" schematic_pos="[2860,590]" />
  <nodo name_node="dwf_left_torso_hmg_bh2" schematic_pos="[2960,590]" />
  <nodo name_node="dwf_left_torso_ac2_bh2" schematic_pos="[3060,590]" />
  <nodo name_node="dwf_left_torso_uac2_bh2" schematic_pos="[3160,590]" />  
  <nodo name_node="dwf_left_torso_rac2_bh2" schematic_pos="[3260,590]" />
  <nodo name_node="dwf_left_torso_lbx2_bh2" schematic_pos="[3360,590]" />  
  <nodo name_node="dwf_left_torso_ac5_bh2" schematic_pos="[3460,590]" />
  <nodo name_node="dwf_left_torso_lbx5_bh2" schematic_pos="[3560,590]" />
  <nodo name_node="dwf_left_torso_uac5_bh2" schematic_pos="[3660,590]" />
  <nodo name_node="dwf_left_torso_lgauss_bh2" schematic_pos="[3760,590]" />
  <nodo name_node="dwf_left_torso_rac5_bh2" schematic_pos="[3860,590]" />
  <nodo name_node="dwf_left_torso_lbx10_bh2" schematic_pos="[3960,590]" />
  <nodo name_node="dwf_left_torso_ac10_bh2" schematic_pos="[4060,590]" />
  <nodo name_node="dwf_left_torso_uac10_bh2" schematic_pos="[4160,590]" />
  <nodo name_node="dwf_left_torso_gauss_bh2" schematic_pos="[4260,590]" />
  <nodo name_node="dwf_left_torso_ac20_bh2" schematic_pos="[4360,590]" />
  <nodo name_node="dwf_left_torso_uac20_bh2" schematic_pos="[4460,590]" />
  <nodo name_node="dwf_left_torso_lbx20_bh2" schematic_pos="[4560,590]" />
  <nodo name_node="dwf_left_torso_hgauss_bh2" schematic_pos="[4660,590]" />
  <nodo name_node="dwf_left_torso_lmg_bh3" schematic_pos="[2760,-710]" />
  <nodo name_node="dwf_left_torso_mg_bh3" schematic_pos="[2860,-710]" />
  <nodo name_node="dwf_left_torso_hmg_bh3" schematic_pos="[2960,-710]" />
  <nodo name_node="dwf_left_torso_ac2_bh3" schematic_pos="[3060,-710]" />
  <nodo name_node="dwf_left_torso_uac2_bh3" schematic_pos="[3160,-710]" />  
  <nodo name_node="dwf_left_torso_rac2_bh3" schematic_pos="[3260,-710]" />
  <nodo name_node="dwf_left_torso_lbx2_bh3" schematic_pos="[3360,-710]" />  
  <nodo name_node="dwf_left_torso_ac5_bh3" schematic_pos="[3460,-710]" />
  <nodo name_node="dwf_left_torso_lbx5_bh3" schematic_pos="[3560,-710]" />
  <nodo name_node="dwf_left_torso_uac5_bh3" schematic_pos="[3660,-710]" />
  <nodo name_node="dwf_left_torso_lgauss_bh3" schematic_pos="[3760,-710]" />
  <nodo name_node="dwf_left_torso_rac5_bh3" schematic_pos="[3860,-710]" />
  <nodo name_node="dwf_left_torso_lbx10_bh3" schematic_pos="[3960,-710]" />
  <nodo name_node="dwf_left_torso_ac10_bh3" schematic_pos="[4060,-710]" />
  <nodo name_node="dwf_left_torso_uac10_bh3" schematic_pos="[4160,-710]" />
  <nodo name_node="dwf_left_torso_gauss_bh3" schematic_pos="[4260,-710]" />
  <nodo name_node="dwf_left_torso_ac20_bh3" schematic_pos="[4360,-710]" />
  <nodo name_node="dwf_left_torso_uac20_bh3" schematic_pos="[4460,-710]" />
  <nodo name_node="dwf_left_torso_lbx20_bh3" schematic_pos="[4560,-710]" />
  <nodo name_node="dwf_left_torso_hgauss_bh3" schematic_pos="[4660,-710]" />
  <nodo name_node="dwf_left_torso_lmg_bh4" schematic_pos="[2760,-880]" />
  <nodo name_node="dwf_left_torso_mg_bh4" schematic_pos="[2860,-880]" />
  <nodo name_node="dwf_left_torso_hmg_bh4" schematic_pos="[2960,-880]" />
  <nodo name_node="dwf_left_torso_ac2_bh4" schematic_pos="[3060,-880]" />
  <nodo name_node="dwf_left_torso_uac2_bh4" schematic_pos="[3160,-880]" />  
  <nodo name_node="dwf_left_torso_rac2_bh4" schematic_pos="[3260,-880]" />
  <nodo name_node="dwf_left_torso_lbx2_bh4" schematic_pos="[3360,-880]" />  
  <nodo name_node="dwf_left_torso_ac5_bh4" schematic_pos="[3460,-880]" />
  <nodo name_node="dwf_left_torso_lbx5_bh4" schematic_pos="[3560,-880]" />
  <nodo name_node="dwf_left_torso_uac5_bh4" schematic_pos="[3660,-880]" />
  <nodo name_node="dwf_left_torso_lgauss_bh4" schematic_pos="[3760,-880]" />
  <nodo name_node="dwf_left_torso_rac5_bh4" schematic_pos="[3860,-880]" />
  <nodo name_node="dwf_left_torso_lbx10_bh4" schematic_pos="[3960,-880]" />
  <nodo name_node="dwf_left_torso_ac10_bh4" schematic_pos="[4060,-880]" />
  <nodo name_node="dwf_left_torso_uac10_bh4" schematic_pos="[4160,-880]" />
  <nodo name_node="dwf_left_torso_gauss_bh4" schematic_pos="[4260,-880]" />
  <nodo name_node="dwf_left_torso_ac20_bh4" schematic_pos="[4360,-880]" />
  <nodo name_node="dwf_left_torso_uac20_bh4" schematic_pos="[4460,-880]" />
  <nodo name_node="dwf_left_torso_lbx20_bh4" schematic_pos="[4560,-880]" />
  <nodo name_node="dwf_left_torso_hgauss_bh4" schematic_pos="[4660,-880]" />
  
  <nodo name_node="dwf_left_torso_narc_mh1" schematic_pos="[2760,760]" />
  <nodo name_node="dwf_left_torso_missile2_mh1" schematic_pos="[2860,760]" />
  <nodo name_node="dwf_left_torso_missile3_mh1" schematic_pos="[2960,760]" />
  <nodo name_node="dwf_left_torso_missile4_mh1" schematic_pos="[3060,760]" />
  <nodo name_node="dwf_left_torso_missile5_mh1" schematic_pos="[3160,760]" />
  <nodo name_node="dwf_left_torso_missile6_mh1" schematic_pos="[3260,760]" />
  <nodo name_node="dwf_left_torso_missile9_mh1" schematic_pos="[3360,760]" />
  <nodo name_node="dwf_left_torso_missile10_mh1" schematic_pos="[3460,760]" />
  <nodo name_node="dwf_left_torso_missile12_mh1" schematic_pos="[3560,760]" />  
  <nodo name_node="dwf_left_torso_missile15_mh1" schematic_pos="[3660,760]" />
  <nodo name_node="dwf_left_torso_missile20_mh1" schematic_pos="[3760,760]" />
  <nodo name_node="dwf_left_torso_rl10_mh1" schematic_pos="[3960,760]" />  
  <nodo name_node="dwf_left_torso_rl15_mh1" schematic_pos="[4060,760]" />    
  <nodo name_node="dwf_left_torso_rl20_mh1" schematic_pos="[4160,760]" />  
  <nodo name_node="dwf_left_torso_narc_mh2" schematic_pos="[2760,1250]" />
  <nodo name_node="dwf_left_torso_missile2_mh2" schematic_pos="[2860,1250]" />
  <nodo name_node="dwf_left_torso_missile3_mh2" schematic_pos="[2960,1250]" />
  <nodo name_node="dwf_left_torso_missile4_mh2" schematic_pos="[3060,1250]" />
  <nodo name_node="dwf_left_torso_missile5_mh2" schematic_pos="[3160,1250]" />
  <nodo name_node="dwf_left_torso_missile6_mh2" schematic_pos="[3260,1250]" />
  <nodo name_node="dwf_left_torso_missile9_mh2" schematic_pos="[3360,1250]" />
  <nodo name_node="dwf_left_torso_missile10_mh2" schematic_pos="[3460,1250]" />
  <nodo name_node="dwf_left_torso_missile12_mh2" schematic_pos="[3560,1250]" />  
  <nodo name_node="dwf_left_torso_missile15_mh2" schematic_pos="[3660,1250]" />
  <nodo name_node="dwf_left_torso_missile20_mh2" schematic_pos="[3760,1250]" />
  <nodo name_node="dwf_left_torso_rl10_mh2" schematic_pos="[3960,1250]" />  
  <nodo name_node="dwf_left_torso_rl15_mh2" schematic_pos="[4060,1250]" />    
  <nodo name_node="dwf_left_torso_rl20_mh2" schematic_pos="[4160,1250]" />  
  <nodo name_node="dwf_left_torso_narc_mh3" schematic_pos="[2760,1740]" />
  <nodo name_node="dwf_left_torso_missile2_mh3" schematic_pos="[2860,1740]" />
  <nodo name_node="dwf_left_torso_missile3_mh3" schematic_pos="[2960,1740]" />
  <nodo name_node="dwf_left_torso_missile4_mh3" schematic_pos="[3060,1740]" />
  <nodo name_node="dwf_left_torso_missile5_mh3" schematic_pos="[3160,1740]" />
  <nodo name_node="dwf_left_torso_missile6_mh3" schematic_pos="[3260,1740]" />
  <nodo name_node="dwf_left_torso_missile9_mh3" schematic_pos="[3360,1740]" />
  <nodo name_node="dwf_left_torso_missile10_mh3" schematic_pos="[3460,1740]" />
  <nodo name_node="dwf_left_torso_missile12_mh3" schematic_pos="[3560,1740]" />  
  <nodo name_node="dwf_left_torso_missile15_mh3" schematic_pos="[3660,1740]" />
  <nodo name_node="dwf_left_torso_missile20_mh3" schematic_pos="[3760,1740]" />
  <nodo name_node="dwf_left_torso_rl10_mh3" schematic_pos="[3960,1740]" />  
  <nodo name_node="dwf_left_torso_rl15_mh3" schematic_pos="[4060,1740]" />    
  <nodo name_node="dwf_left_torso_rl20_mh3" schematic_pos="[4160,1740]" />  
  <nodo name_node="dwf_left_torso_narc_mh4" schematic_pos="[2760,-1370]" />
  <nodo name_node="dwf_left_torso_missile2_mh4" schematic_pos="[2860,-1370]" />
  <nodo name_node="dwf_left_torso_missile3_mh4" schematic_pos="[2960,-1370]" />
  <nodo name_node="dwf_left_torso_missile4_mh4" schematic_pos="[3060,-1370]" />
  <nodo name_node="dwf_left_torso_missile5_mh4" schematic_pos="[3160,-1370]" />
  <nodo name_node="dwf_left_torso_missile6_mh4" schematic_pos="[3260,-1370]" />
  <nodo name_node="dwf_left_torso_missile9_mh4" schematic_pos="[3360,-1370]" />
  <nodo name_node="dwf_left_torso_missile10_mh4" schematic_pos="[3460,-1370]" />
  <nodo name_node="dwf_left_torso_missile12_mh4" schematic_pos="[3560,-1370]" />  
  <nodo name_node="dwf_left_torso_missile15_mh4" schematic_pos="[3660,-1370]" />
  <nodo name_node="dwf_left_torso_missile20_mh4" schematic_pos="[3760,-1370]" />
  <nodo name_node="dwf_left_torso_rl10_mh4" schematic_pos="[3960,-1370]" />  
  <nodo name_node="dwf_left_torso_rl15_mh4" schematic_pos="[4060,-1370]" />    
  <nodo name_node="dwf_left_torso_rl20_mh4" schematic_pos="[4160,-1370]" />  
  <nodo name_node="dwf_left_torso_narc_mh5" schematic_pos="[2760,-1860]" />
  <nodo name_node="dwf_left_torso_missile2_mh5" schematic_pos="[2860,-1860]" />
  <nodo name_node="dwf_left_torso_missile3_mh5" schematic_pos="[2960,-1860]" />
  <nodo name_node="dwf_left_torso_missile4_mh5" schematic_pos="[3060,-1860]" />
  <nodo name_node="dwf_left_torso_missile5_mh5" schematic_pos="[3160,-1860]" />
  <nodo name_node="dwf_left_torso_missile6_mh5" schematic_pos="[3260,-1860]" />
  <nodo name_node="dwf_left_torso_missile9_mh5" schematic_pos="[3360,-1860]" />
  <nodo name_node="dwf_left_torso_missile10_mh5" schematic_pos="[3460,-1860]" />
  <nodo name_node="dwf_left_torso_missile12_mh5" schematic_pos="[3560,-1860]" />  
  <nodo name_node="dwf_left_torso_missile15_mh5" schematic_pos="[3660,-1860]" />
  <nodo name_node="dwf_left_torso_missile20_mh5" schematic_pos="[3760,-1860]" />
  <nodo name_node="dwf_left_torso_rl10_mh5" schematic_pos="[3960,-1860]" />  
  <nodo name_node="dwf_left_torso_rl15_mh5" schematic_pos="[4060,-1860]" />    
  <nodo name_node="dwf_left_torso_rl20_mh5" schematic_pos="[4160,-1860]" />  
  
  
  
  <nodo name_node="dwf_left_arm_forearm_ams_ah1" schematic_pos="[4860,000]" />
  <nodo name_node="dwf_left_arm_forearm_lams_ah1" schematic_pos="[4960,000]" />  
  <nodo name_node="dwf_left_arm_forearm_ams_ah2" schematic_pos="[4860,-150]" />
  <nodo name_node="dwf_left_arm_forearm_lams_ah2" schematic_pos="[4960,-150]" />  
  
  <nodo name_node="dwf_left_arm_forearm_hppc_eh1" schematic_pos="[5360,150]" />
  <nodo name_node="dwf_left_arm_forearm_ppc_eh1" schematic_pos="[5260,150]" />  
  <nodo name_node="dwf_left_arm_forearm_snppc_eh1" schematic_pos="[5160,150]" />
  <nodo name_node="dwf_left_arm_forearm_lppc_eh1" schematic_pos="[5060,150]" />
  <nodo name_node="dwf_left_arm_forearm_laser_eh1" schematic_pos="[4960,150]" />
  <nodo name_node="dwf_left_arm_forearm_flamer_eh1" schematic_pos="[4860,150]" />
  <nodo name_node="dwf_left_arm_forearm_hppc_eh2" schematic_pos="[5360,280]" />
  <nodo name_node="dwf_left_arm_forearm_ppc_eh2" schematic_pos="[5260,280]" />  
  <nodo name_node="dwf_left_arm_forearm_snppc_eh2" schematic_pos="[5160,280]" />
  <nodo name_node="dwf_left_arm_forearm_lppc_eh2" schematic_pos="[5060,280]" />
  <nodo name_node="dwf_left_arm_forearm_laser_eh2" schematic_pos="[4960,280]" />
  <nodo name_node="dwf_left_arm_forearm_flamer_eh2" schematic_pos="[4860,280]" />
  <nodo name_node="dwf_left_arm_forearm_hppc_eh3" schematic_pos="[5360,280]" />
  <nodo name_node="dwf_left_arm_forearm_ppc_eh3" schematic_pos="[5260,280]" />  
  <nodo name_node="dwf_left_arm_forearm_snppc_eh3" schematic_pos="[5160,280]" />
  <nodo name_node="dwf_left_arm_forearm_lppc_eh3" schematic_pos="[5060,280]" />
  <nodo name_node="dwf_left_arm_forearm_laser_eh3" schematic_pos="[4960,280]" />
  <nodo name_node="dwf_left_arm_forearm_flamer_eh3" schematic_pos="[4860,280]" />
  <nodo name_node="dwf_left_arm_forearm_hppc_eh4" schematic_pos="[5360,-410]" />
  <nodo name_node="dwf_left_arm_forearm_ppc_eh4" schematic_pos="[5260,-410]" />  
  <nodo name_node="dwf_left_arm_forearm_snppc_eh4" schematic_pos="[5160,-410]" />
  <nodo name_node="dwf_left_arm_forearm_lppc_eh4" schematic_pos="[5060,-410]" />
  <nodo name_node="dwf_left_arm_forearm_laser_eh4" schematic_pos="[4960,-410]" />
  <nodo name_node="dwf_left_arm_forearm_flamer_eh4" schematic_pos="[4860,-410]" />
  <nodo name_node="dwf_left_arm_forearm_hppc_eh5" schematic_pos="[5360,-540]" />
  <nodo name_node="dwf_left_arm_forearm_ppc_eh5" schematic_pos="[5260,-540]" />  
  <nodo name_node="dwf_left_arm_forearm_snppc_eh5" schematic_pos="[5160,-540]" />
  <nodo name_node="dwf_left_arm_forearm_lppc_eh5" schematic_pos="[5060,-540]" />
  <nodo name_node="dwf_left_arm_forearm_laser_eh5" schematic_pos="[4960,-540]" />
  <nodo name_node="dwf_left_arm_forearm_flamer_eh5" schematic_pos="[4860,-540]" />
  
  <nodo name_node="dwf_left_arm_forearm_lmg_bh1" schematic_pos="[4860,420]" />
  <nodo name_node="dwf_left_arm_forearm_mg_bh1" schematic_pos="[4960,420]" />
  <nodo name_node="dwf_left_arm_forearm_hmg_bh1" schematic_pos="[5060,420]" />
  <nodo name_node="dwf_left_arm_forearm_ac2_bh1" schematic_pos="[5160,420]" />
  <nodo name_node="dwf_left_arm_forearm_uac2_bh1" schematic_pos="[5260,420]" />  
  <nodo name_node="dwf_left_arm_forearm_rac2_bh1" schematic_pos="[5360,420]" />
  <nodo name_node="dwf_left_arm_forearm_lbx2_bh1" schematic_pos="[5460,420]" />  
  <nodo name_node="dwf_left_arm_forearm_ac5_bh1" schematic_pos="[5560,420]" />
  <nodo name_node="dwf_left_arm_forearm_lbx5_bh1" schematic_pos="[5660,420]" />
  <nodo name_node="dwf_left_arm_forearm_uac5_bh1" schematic_pos="[5760,420]" />
  <nodo name_node="dwf_left_arm_forearm_lgauss_bh1" schematic_pos="[5860,420]" />
  <nodo name_node="dwf_left_arm_forearm_rac5_bh1" schematic_pos="[5960,420]" />
  <nodo name_node="dwf_left_arm_forearm_lbx10_bh1" schematic_pos="[6060,420]" />
  <nodo name_node="dwf_left_arm_forearm_ac10_bh1" schematic_pos="[6160,420]" />
  <nodo name_node="dwf_left_arm_forearm_uac10_bh1" schematic_pos="[6260,420]" />
  <nodo name_node="dwf_left_arm_forearm_gauss_bh1" schematic_pos="[6360,420]" />
  <nodo name_node="dwf_left_arm_forearm_ac20_bh1" schematic_pos="[6460,420]" />
  <nodo name_node="dwf_left_arm_forearm_uac20_bh1" schematic_pos="[6560,420]" />
  <nodo name_node="dwf_left_arm_forearm_lbx20_bh1" schematic_pos="[6660,420]" />
  <nodo name_node="dwf_left_arm_forearm_hgauss_bh1" schematic_pos="[6760,420]" />
  <nodo name_node="dwf_left_arm_forearm_lmg_bh2" schematic_pos="[4860,590]" />
  <nodo name_node="dwf_left_arm_forearm_mg_bh2" schematic_pos="[4960,590]" />
  <nodo name_node="dwf_left_arm_forearm_hmg_bh2" schematic_pos="[5060,590]" />
  <nodo name_node="dwf_left_arm_forearm_ac2_bh2" schematic_pos="[5160,590]" />
  <nodo name_node="dwf_left_arm_forearm_uac2_bh2" schematic_pos="[5260,590]" />  
  <nodo name_node="dwf_left_arm_forearm_rac2_bh2" schematic_pos="[5360,590]" />
  <nodo name_node="dwf_left_arm_forearm_lbx2_bh2" schematic_pos="[5460,590]" />  
  <nodo name_node="dwf_left_arm_forearm_ac5_bh2" schematic_pos="[5560,590]" />
  <nodo name_node="dwf_left_arm_forearm_lbx5_bh2" schematic_pos="[5660,590]" />
  <nodo name_node="dwf_left_arm_forearm_uac5_bh2" schematic_pos="[5760,590]" />
  <nodo name_node="dwf_left_arm_forearm_lgauss_bh2" schematic_pos="[5860,590]" />
  <nodo name_node="dwf_left_arm_forearm_rac5_bh2" schematic_pos="[5960,590]" />
  <nodo name_node="dwf_left_arm_forearm_lbx10_bh2" schematic_pos="[6060,590]" />
  <nodo name_node="dwf_left_arm_forearm_ac10_bh2" schematic_pos="[6160,590]" />
  <nodo name_node="dwf_left_arm_forearm_uac10_bh2" schematic_pos="[6260,590]" />
  <nodo name_node="dwf_left_arm_forearm_gauss_bh2" schematic_pos="[6360,590]" />
  <nodo name_node="dwf_left_arm_forearm_ac20_bh2" schematic_pos="[6460,590]" />
  <nodo name_node="dwf_left_arm_forearm_uac20_bh2" schematic_pos="[6560,590]" />
  <nodo name_node="dwf_left_arm_forearm_lbx20_bh2" schematic_pos="[6660,590]" />
  <nodo name_node="dwf_left_arm_forearm_hgauss_bh2" schematic_pos="[6760,590]" />
  <nodo name_node="dwf_left_arm_forearm_lmg_bh3" schematic_pos="[4860,-710]" />
  <nodo name_node="dwf_left_arm_forearm_mg_bh3" schematic_pos="[4960,-710]" />
  <nodo name_node="dwf_left_arm_forearm_hmg_bh3" schematic_pos="[5060,-710]" />
  <nodo name_node="dwf_left_arm_forearm_ac2_bh3" schematic_pos="[5160,-710]" />
  <nodo name_node="dwf_left_arm_forearm_uac2_bh3" schematic_pos="[5260,-710]" />  
  <nodo name_node="dwf_left_arm_forearm_rac2_bh3" schematic_pos="[5360,-710]" />
  <nodo name_node="dwf_left_arm_forearm_lbx2_bh3" schematic_pos="[5460,-710]" />  
  <nodo name_node="dwf_left_arm_forearm_ac5_bh3" schematic_pos="[5560,-710]" />
  <nodo name_node="dwf_left_arm_forearm_lbx5_bh3" schematic_pos="[5660,-710]" />
  <nodo name_node="dwf_left_arm_forearm_uac5_bh3" schematic_pos="[5760,-710]" />
  <nodo name_node="dwf_left_arm_forearm_lgauss_bh3" schematic_pos="[5860,-710]" />
  <nodo name_node="dwf_left_arm_forearm_rac5_bh3" schematic_pos="[5960,-710]" />
  <nodo name_node="dwf_left_arm_forearm_lbx10_bh3" schematic_pos="[6060,-710]" />
  <nodo name_node="dwf_left_arm_forearm_ac10_bh3" schematic_pos="[6160,-710]" />
  <nodo name_node="dwf_left_arm_forearm_uac10_bh3" schematic_pos="[6260,-710]" />
  <nodo name_node="dwf_left_arm_forearm_gauss_bh3" schematic_pos="[6360,-710]" />
  <nodo name_node="dwf_left_arm_forearm_ac20_bh3" schematic_pos="[6460,-710]" />
  <nodo name_node="dwf_left_arm_forearm_uac20_bh3" schematic_pos="[6560,-710]" />
  <nodo name_node="dwf_left_arm_forearm_lbx20_bh3" schematic_pos="[6660,-710]" />
  <nodo name_node="dwf_left_arm_forearm_hgauss_bh3" schematic_pos="[6760,-710]" />
  <nodo name_node="dwf_left_arm_forearm_lmg_bh4" schematic_pos="[4860,-880]" />
  <nodo name_node="dwf_left_arm_forearm_mg_bh4" schematic_pos="[4960,-880]" />
  <nodo name_node="dwf_left_arm_forearm_hmg_bh4" schematic_pos="[5060,-880]" />
  <nodo name_node="dwf_left_arm_forearm_ac2_bh4" schematic_pos="[5160,-880]" />
  <nodo name_node="dwf_left_arm_forearm_uac2_bh4" schematic_pos="[5260,-880]" />  
  <nodo name_node="dwf_left_arm_forearm_rac2_bh4" schematic_pos="[5360,-880]" />
  <nodo name_node="dwf_left_arm_forearm_lbx2_bh4" schematic_pos="[5460,-880]" />  
  <nodo name_node="dwf_left_arm_forearm_ac5_bh4" schematic_pos="[5560,-880]" />
  <nodo name_node="dwf_left_arm_forearm_lbx5_bh4" schematic_pos="[5660,-880]" />
  <nodo name_node="dwf_left_arm_forearm_uac5_bh4" schematic_pos="[5760,-880]" />
  <nodo name_node="dwf_left_arm_forearm_lgauss_bh4" schematic_pos="[5860,-880]" />
  <nodo name_node="dwf_left_arm_forearm_rac5_bh4" schematic_pos="[5960,-880]" />
  <nodo name_node="dwf_left_arm_forearm_lbx10_bh4" schematic_pos="[6060,-880]" />
  <nodo name_node="dwf_left_arm_forearm_ac10_bh4" schematic_pos="[6160,-880]" />
  <nodo name_node="dwf_left_arm_forearm_uac10_bh4" schematic_pos="[6260,-880]" />
  <nodo name_node="dwf_left_arm_forearm_gauss_bh4" schematic_pos="[6360,-880]" />
  <nodo name_node="dwf_left_arm_forearm_ac20_bh4" schematic_pos="[6460,-880]" />
  <nodo name_node="dwf_left_arm_forearm_uac20_bh4" schematic_pos="[6560,-880]" />
  <nodo name_node="dwf_left_arm_forearm_lbx20_bh4" schematic_pos="[6660,-880]" />
  <nodo name_node="dwf_left_arm_forearm_hgauss_bh4" schematic_pos="[6760,-880]" />
  
  <nodo name_node="dwf_left_arm_forearm_narc_mh1" schematic_pos="[4860,760]" />
  <nodo name_node="dwf_left_arm_forearm_missile2_mh1" schematic_pos="[4960,760]" />
  <nodo name_node="dwf_left_arm_forearm_missile3_mh1" schematic_pos="[5060,760]" />
  <nodo name_node="dwf_left_arm_forearm_missile4_mh1" schematic_pos="[5160,760]" />
  <nodo name_node="dwf_left_arm_forearm_missile5_mh1" schematic_pos="[5260,760]" />
  <nodo name_node="dwf_left_arm_forearm_missile6_mh1" schematic_pos="[5360,760]" />
  <nodo name_node="dwf_left_arm_forearm_missile9_mh1" schematic_pos="[5460,760]" />
  <nodo name_node="dwf_left_arm_forearm_missile10_mh1" schematic_pos="[5560,760]" />
  <nodo name_node="dwf_left_arm_forearm_missile12_mh1" schematic_pos="[5660,760]" />  
  <nodo name_node="dwf_left_arm_forearm_missile15_mh1" schematic_pos="[5760,760]" />
  <nodo name_node="dwf_left_arm_forearm_missile20_mh1" schematic_pos="[5860,760]" />
  <nodo name_node="dwf_left_arm_forearm_rl10_mh1" schematic_pos="[6060,760]" />  
  <nodo name_node="dwf_left_arm_forearm_rl15_mh1" schematic_pos="[6160,760]" />    
  <nodo name_node="dwf_left_arm_forearm_rl20_mh1" schematic_pos="[6260,760]" />  
  <nodo name_node="dwf_left_arm_forearm_narc_mh2" schematic_pos="[4860,1250]" />
  <nodo name_node="dwf_left_arm_forearm_missile2_mh2" schematic_pos="[4960,1250]" />
  <nodo name_node="dwf_left_arm_forearm_missile3_mh2" schematic_pos="[5060,1250]" />
  <nodo name_node="dwf_left_arm_forearm_missile4_mh2" schematic_pos="[5160,1250]" />
  <nodo name_node="dwf_left_arm_forearm_missile5_mh2" schematic_pos="[5260,1250]" />
  <nodo name_node="dwf_left_arm_forearm_missile6_mh2" schematic_pos="[5360,1250]" />
  <nodo name_node="dwf_left_arm_forearm_missile9_mh2" schematic_pos="[5460,1250]" />
  <nodo name_node="dwf_left_arm_forearm_missile10_mh2" schematic_pos="[5560,1250]" />
  <nodo name_node="dwf_left_arm_forearm_missile12_mh2" schematic_pos="[5660,1250]" />  
  <nodo name_node="dwf_left_arm_forearm_missile15_mh2" schematic_pos="[5760,1250]" />
  <nodo name_node="dwf_left_arm_forearm_missile20_mh2" schematic_pos="[5860,1250]" />
  <nodo name_node="dwf_left_arm_forearm_rl10_mh2" schematic_pos="[6060,1250]" />  
  <nodo name_node="dwf_left_arm_forearm_rl15_mh2" schematic_pos="[6160,1250]" />    
  <nodo name_node="dwf_left_arm_forearm_rl20_mh2" schematic_pos="[6260,1250]" />    
  <nodo name_node="dwf_left_arm_forearm_narc_mh3" schematic_pos="[4860,1740]" />
  <nodo name_node="dwf_left_arm_forearm_missile2_mh3" schematic_pos="[4960,1740]" />
  <nodo name_node="dwf_left_arm_forearm_missile3_mh3" schematic_pos="[5060,1740]" />
  <nodo name_node="dwf_left_arm_forearm_missile4_mh3" schematic_pos="[5160,1740]" />
  <nodo name_node="dwf_left_arm_forearm_missile5_mh3" schematic_pos="[5260,1740]" />
  <nodo name_node="dwf_left_arm_forearm_missile6_mh3" schematic_pos="[5360,1740]" />
  <nodo name_node="dwf_left_arm_forearm_missile9_mh3" schematic_pos="[5460,1740]" />
  <nodo name_node="dwf_left_arm_forearm_missile10_mh3" schematic_pos="[5560,1740]" />
  <nodo name_node="dwf_left_arm_forearm_missile12_mh3" schematic_pos="[5660,1740]" />  
  <nodo name_node="dwf_left_arm_forearm_missile15_mh3" schematic_pos="[5760,1740]" />
  <nodo name_node="dwf_left_arm_forearm_missile20_mh3" schematic_pos="[5860,1740]" />
  <nodo name_node="dwf_left_arm_forearm_rl10_mh3" schematic_pos="[6060,1740]" />  
  <nodo name_node="dwf_left_arm_forearm_rl15_mh3" schematic_pos="[6160,1740]" />    
  <nodo name_node="dwf_left_arm_forearm_rl20_mh3" schematic_pos="[6260,1740]" />    
  <nodo name_node="dwf_left_arm_forearm_narc_mh4" schematic_pos="[4860,-1370]" />
  <nodo name_node="dwf_left_arm_forearm_missile2_mh4" schematic_pos="[4960,-1370]" />
  <nodo name_node="dwf_left_arm_forearm_missile3_mh4" schematic_pos="[5060,-1370]" />
  <nodo name_node="dwf_left_arm_forearm_missile4_mh4" schematic_pos="[5160,-1370]" />
  <nodo name_node="dwf_left_arm_forearm_missile5_mh4" schematic_pos="[5260,-1370]" />
  <nodo name_node="dwf_left_arm_forearm_missile6_mh4" schematic_pos="[5360,-1370]" />
  <nodo name_node="dwf_left_arm_forearm_missile9_mh4" schematic_pos="[5460,-1370]" />
  <nodo name_node="dwf_left_arm_forearm_missile10_mh4" schematic_pos="[5560,-1370]" />
  <nodo name_node="dwf_left_arm_forearm_missile12_mh4" schematic_pos="[5660,-1370]" />  
  <nodo name_node="dwf_left_arm_forearm_missile15_mh4" schematic_pos="[5760,-1370]" />
  <nodo name_node="dwf_left_arm_forearm_missile20_mh4" schematic_pos="[5860,-1370]" />
  <nodo name_node="dwf_left_arm_forearm_rl10_mh4" schematic_pos="[6060,-1370]" />  
  <nodo name_node="dwf_left_arm_forearm_rl15_mh4" schematic_pos="[6160,-1370]" />    
  <nodo name_node="dwf_left_arm_forearm_rl20_mh4" schematic_pos="[6260,-1370]" />  
  <nodo name_node="dwf_left_arm_forearm_narc_mh5" schematic_pos="[4860,-1860]" />
  <nodo name_node="dwf_left_arm_forearm_missile2_mh5" schematic_pos="[4960,-1860]" />
  <nodo name_node="dwf_left_arm_forearm_missile3_mh5" schematic_pos="[5060,-1860]" />
  <nodo name_node="dwf_left_arm_forearm_missile4_mh5" schematic_pos="[5160,-1860]" />
  <nodo name_node="dwf_left_arm_forearm_missile5_mh5" schematic_pos="[5260,-1860]" />
  <nodo name_node="dwf_left_arm_forearm_missile6_mh5" schematic_pos="[5360,-1860]" />
  <nodo name_node="dwf_left_arm_forearm_missile9_mh5" schematic_pos="[5460,-1860]" />
  <nodo name_node="dwf_left_arm_forearm_missile10_mh5" schematic_pos="[5560,-1860]" />
  <nodo name_node="dwf_left_arm_forearm_missile12_mh5" schematic_pos="[5660,-1860]" />  
  <nodo name_node="dwf_left_arm_forearm_missile15_mh5" schematic_pos="[5760,-1860]" />
  <nodo name_node="dwf_left_arm_forearm_missile20_mh5" schematic_pos="[5860,-1860]" />
  <nodo name_node="dwf_left_arm_forearm_rl10_mh5" schematic_pos="[6060,-1860]" />  
  <nodo name_node="dwf_left_arm_forearm_rl15_mh5" schematic_pos="[6160,-1860]" />    
  <nodo name_node="dwf_left_arm_forearm_rl20_mh5" schematic_pos="[6260,-1860]" />   
  
  
  
  <nodo name_node="dwf_right_torso_ams_ah1" schematic_pos="[300,000]" />
  <nodo name_node="dwf_right_torso_lams_ah1" schematic_pos="[200,000]" />  
  <nodo name_node="dwf_right_torso_ams_ah2" schematic_pos="[300,-150]" />
  <nodo name_node="dwf_right_torso_lams_ah2" schematic_pos="[200,-150]" />  
  
  <nodo name_node="dwf_right_torso_hppc_eh1" schematic_pos="[-200,150]" />
  <nodo name_node="dwf_right_torso_ppc_eh1" schematic_pos="[-100,150]" />  
  <nodo name_node="dwf_right_torso_snppc_eh1" schematic_pos="[000,150]" />
  <nodo name_node="dwf_right_torso_lppc_eh1" schematic_pos="[100,150]" />
  <nodo name_node="dwf_right_torso_laser_eh1" schematic_pos="[200,150]" />
  <nodo name_node="dwf_right_torso_flamer_eh1" schematic_pos="[300,150]" />
  <nodo name_node="dwf_right_torso_hppc_eh2" schematic_pos="[-200,280]" />
  <nodo name_node="dwf_right_torso_ppc_eh2" schematic_pos="[-100,280]" />  
  <nodo name_node="dwf_right_torso_snppc_eh2" schematic_pos="[000,280]" />
  <nodo name_node="dwf_right_torso_lppc_eh2" schematic_pos="[100,280]" />
  <nodo name_node="dwf_right_torso_laser_eh2" schematic_pos="[200,280]" />
  <nodo name_node="dwf_right_torso_flamer_eh2" schematic_pos="[300,280]" />
  <nodo name_node="dwf_right_torso_hppc_eh3" schematic_pos="[-200,-280]" />
  <nodo name_node="dwf_right_torso_ppc_eh3" schematic_pos="[-100,-280]" />  
  <nodo name_node="dwf_right_torso_snppc_eh3" schematic_pos="[000,-280]" />
  <nodo name_node="dwf_right_torso_lppc_eh3" schematic_pos="[100,-280]" />
  <nodo name_node="dwf_right_torso_laser_eh3" schematic_pos="[200,-280]" />
  <nodo name_node="dwf_right_torso_flamer_eh3" schematic_pos="[300,-280]" />
  <nodo name_node="dwf_right_torso_hppc_eh4" schematic_pos="[-200,-410]" />
  <nodo name_node="dwf_right_torso_ppc_eh4" schematic_pos="[-100,-410]" />  
  <nodo name_node="dwf_right_torso_snppc_eh4" schematic_pos="[000,-410]" />
  <nodo name_node="dwf_right_torso_lppc_eh4" schematic_pos="[100,-410]" />
  <nodo name_node="dwf_right_torso_laser_eh4" schematic_pos="[200,-410]" />
  <nodo name_node="dwf_right_torso_flamer_eh4" schematic_pos="[300,-410]" />
  <nodo name_node="dwf_right_torso_hppc_eh5" schematic_pos="[-200,-540]" />
  <nodo name_node="dwf_right_torso_ppc_eh5" schematic_pos="[-100,-540]" />  
  <nodo name_node="dwf_right_torso_snppc_eh5" schematic_pos="[000,-540]" />
  <nodo name_node="dwf_right_torso_lppc_eh5" schematic_pos="[100,-540]" />
  <nodo name_node="dwf_right_torso_laser_eh5" schematic_pos="[200,-540]" />
  <nodo name_node="dwf_right_torso_flamer_eh5" schematic_pos="[300,-540]" />

  <nodo name_node="dwf_right_torso_lmg_bh1" schematic_pos="[300,420]" />
  <nodo name_node="dwf_right_torso_mg_bh1" schematic_pos="[200,420]" />
  <nodo name_node="dwf_right_torso_hmg_bh1" schematic_pos="[100,420]" />
  <nodo name_node="dwf_right_torso_ac2_bh1" schematic_pos="[000,420]" />
  <nodo name_node="dwf_right_torso_uac2_bh1" schematic_pos="[-100,420]" />  
  <nodo name_node="dwf_right_torso_rac2_bh1" schematic_pos="[-200,420]" />
  <nodo name_node="dwf_right_torso_lbx2_bh1" schematic_pos="[-300,420]" />  
  <nodo name_node="dwf_right_torso_ac5_bh1" schematic_pos="[-400,420]" />
  <nodo name_node="dwf_right_torso_lbx5_bh1" schematic_pos="[-500,420]" />
  <nodo name_node="dwf_right_torso_uac5_bh1" schematic_pos="[-600,420]" />
  <nodo name_node="dwf_right_torso_lgauss_bh1" schematic_pos="[-700,420]" />
  <nodo name_node="dwf_right_torso_rac5_bh1" schematic_pos="[-800,420]" />
  <nodo name_node="dwf_right_torso_lbx10_bh1" schematic_pos="[-900,420]" />
  <nodo name_node="dwf_right_torso_ac10_bh1" schematic_pos="[-1000,420]" />
  <nodo name_node="dwf_right_torso_uac10_bh1" schematic_pos="[-1100,420]" />
  <nodo name_node="dwf_right_torso_gauss_bh1" schematic_pos="[-1200,420]" />
  <nodo name_node="dwf_right_torso_ac20_bh1" schematic_pos="[-1300,420]" />
  <nodo name_node="dwf_right_torso_uac20_bh1" schematic_pos="[-1400,420]" />
  <nodo name_node="dwf_right_torso_lbx20_bh1" schematic_pos="[-1500,420]" />
  <nodo name_node="dwf_right_torso_hgauss_bh1" schematic_pos="[-1600,420]" />
  <nodo name_node="dwf_right_torso_lmg_bh2" schematic_pos="[300,590]" />
  <nodo name_node="dwf_right_torso_mg_bh2" schematic_pos="[200,590]" />
  <nodo name_node="dwf_right_torso_hmg_bh2" schematic_pos="[100,590]" />
  <nodo name_node="dwf_right_torso_ac2_bh2" schematic_pos="[000,590]" />
  <nodo name_node="dwf_right_torso_uac2_bh2" schematic_pos="[-100,590]" />  
  <nodo name_node="dwf_right_torso_rac2_bh2" schematic_pos="[-200,590]" />
  <nodo name_node="dwf_right_torso_lbx2_bh2" schematic_pos="[-300,590]" />  
  <nodo name_node="dwf_right_torso_ac5_bh2" schematic_pos="[-400,590]" />
  <nodo name_node="dwf_right_torso_lbx5_bh2" schematic_pos="[-500,590]" />
  <nodo name_node="dwf_right_torso_uac5_bh2" schematic_pos="[-600,590]" />
  <nodo name_node="dwf_right_torso_lgauss_bh2" schematic_pos="[-700,590]" />
  <nodo name_node="dwf_right_torso_rac5_bh2" schematic_pos="[-800,590]" />
  <nodo name_node="dwf_right_torso_lbx10_bh2" schematic_pos="[-900,590]" />
  <nodo name_node="dwf_right_torso_ac10_bh2" schematic_pos="[-1000,590]" />
  <nodo name_node="dwf_right_torso_uac10_bh2" schematic_pos="[-1100,590]" />
  <nodo name_node="dwf_right_torso_gauss_bh2" schematic_pos="[-1200,590]" />
  <nodo name_node="dwf_right_torso_ac20_bh2" schematic_pos="[-1300,590]" />
  <nodo name_node="dwf_right_torso_uac20_bh2" schematic_pos="[-1400,590]" />
  <nodo name_node="dwf_right_torso_lbx20_bh2" schematic_pos="[-1500,590]" />
  <nodo name_node="dwf_right_torso_hgauss_bh2" schematic_pos="[-1600,590]" />
  <nodo name_node="dwf_right_torso_lmg_bh3" schematic_pos="[300,-710]" />
  <nodo name_node="dwf_right_torso_mg_bh3" schematic_pos="[200,-710]" />
  <nodo name_node="dwf_right_torso_hmg_bh3" schematic_pos="[100,-710]" />
  <nodo name_node="dwf_right_torso_ac2_bh3" schematic_pos="[000,-710]" />
  <nodo name_node="dwf_right_torso_uac2_bh3" schematic_pos="[-100,-710]" />  
  <nodo name_node="dwf_right_torso_rac2_bh3" schematic_pos="[-200,-710]" />
  <nodo name_node="dwf_right_torso_lbx2_bh3" schematic_pos="[-300,-710]" />  
  <nodo name_node="dwf_right_torso_ac5_bh3" schematic_pos="[-400,-710]" />
  <nodo name_node="dwf_right_torso_lbx5_bh3" schematic_pos="[-500,-710]" />
  <nodo name_node="dwf_right_torso_uac5_bh3" schematic_pos="[-600,-710]" />
  <nodo name_node="dwf_right_torso_lgauss_bh3" schematic_pos="[-700,-710]" />
  <nodo name_node="dwf_right_torso_rac5_bh3" schematic_pos="[-800,-710]" />
  <nodo name_node="dwf_right_torso_lbx10_bh3" schematic_pos="[-900,-710]" />
  <nodo name_node="dwf_right_torso_ac10_bh3" schematic_pos="[-1000,-710]" />
  <nodo name_node="dwf_right_torso_uac10_bh3" schematic_pos="[-1100,-710]" />
  <nodo name_node="dwf_right_torso_gauss_bh3" schematic_pos="[-1200,-710]" />
  <nodo name_node="dwf_right_torso_ac20_bh3" schematic_pos="[-1300,-710]" />
  <nodo name_node="dwf_right_torso_uac20_bh3" schematic_pos="[-1400,-710]" />
  <nodo name_node="dwf_right_torso_lbx20_bh3" schematic_pos="[-1500,-710]" />
  <nodo name_node="dwf_right_torso_hgauss_bh3" schematic_pos="[-1600,-710]" />
  <nodo name_node="dwf_right_torso_lmg_bh4" schematic_pos="[300,-880]" />
  <nodo name_node="dwf_right_torso_mg_bh4" schematic_pos="[200,-880]" />
  <nodo name_node="dwf_right_torso_hmg_bh4" schematic_pos="[100,-880]" />
  <nodo name_node="dwf_right_torso_ac2_bh4" schematic_pos="[000,-880]" />
  <nodo name_node="dwf_right_torso_uac2_bh4" schematic_pos="[-100,-880]" />  
  <nodo name_node="dwf_right_torso_rac2_bh4" schematic_pos="[-200,-880]" />
  <nodo name_node="dwf_right_torso_lbx2_bh4" schematic_pos="[-300,-880]" />  
  <nodo name_node="dwf_right_torso_ac5_bh4" schematic_pos="[-400,-880]" />
  <nodo name_node="dwf_right_torso_lbx5_bh4" schematic_pos="[-500,-880]" />
  <nodo name_node="dwf_right_torso_uac5_bh4" schematic_pos="[-600,-880]" />
  <nodo name_node="dwf_right_torso_lgauss_bh4" schematic_pos="[-700,-880]" />
  <nodo name_node="dwf_right_torso_rac5_bh4" schematic_pos="[-800,-880]" />
  <nodo name_node="dwf_right_torso_lbx10_bh4" schematic_pos="[-900,-880]" />
  <nodo name_node="dwf_right_torso_ac10_bh4" schematic_pos="[-1000,-880]" />
  <nodo name_node="dwf_right_torso_uac10_bh4" schematic_pos="[-1100,-880]" />
  <nodo name_node="dwf_right_torso_gauss_bh4" schematic_pos="[-1200,-880]" />
  <nodo name_node="dwf_right_torso_ac20_bh4" schematic_pos="[-1300,-880]" />
  <nodo name_node="dwf_right_torso_uac20_bh4" schematic_pos="[-1400,-880]" />
  <nodo name_node="dwf_right_torso_lbx20_bh4" schematic_pos="[-1500,-880]" />
  <nodo name_node="dwf_right_torso_hgauss_bh4" schematic_pos="[-1600,-880]" />

  <nodo name_node="dwf_right_torso_narc_mh1" schematic_pos="[300,760]" />
  <nodo name_node="dwf_right_torso_missile2_mh1" schematic_pos="[200,760]" />
  <nodo name_node="dwf_right_torso_missile3_mh1" schematic_pos="[100,760]" />
  <nodo name_node="dwf_right_torso_missile4_mh1" schematic_pos="[000,760]" />
  <nodo name_node="dwf_right_torso_missile5_mh1" schematic_pos="[-100,760]" />
  <nodo name_node="dwf_right_torso_missile6_mh1" schematic_pos="[-200,760]" />
  <nodo name_node="dwf_right_torso_missile9_mh1" schematic_pos="[-300,760]" />
  <nodo name_node="dwf_right_torso_missile10_mh1" schematic_pos="[-400,760]" />
  <nodo name_node="dwf_right_torso_missile12_mh1" schematic_pos="[-500,760]" />  
  <nodo name_node="dwf_right_torso_missile15_mh1" schematic_pos="[-600,760]" />
  <nodo name_node="dwf_right_torso_missile20_mh1" schematic_pos="[-700,760]" />
  <nodo name_node="dwf_right_torso_rl10_mh1" schematic_pos="[-900,760]" />  
  <nodo name_node="dwf_right_torso_rl15_mh1" schematic_pos="[-1000,760]" />    
  <nodo name_node="dwf_right_torso_rl20_mh1" schematic_pos="[-1100,760]" />  
  <nodo name_node="dwf_right_torso_narc_mh2" schematic_pos="[300,1250]" />
  <nodo name_node="dwf_right_torso_missile2_mh2" schematic_pos="[200,1250]" />
  <nodo name_node="dwf_right_torso_missile3_mh2" schematic_pos="[100,1250]" />
  <nodo name_node="dwf_right_torso_missile4_mh2" schematic_pos="[000,1250]" />
  <nodo name_node="dwf_right_torso_missile5_mh2" schematic_pos="[-100,1250]" />
  <nodo name_node="dwf_right_torso_missile6_mh2" schematic_pos="[-200,1250]" />
  <nodo name_node="dwf_right_torso_missile9_mh2" schematic_pos="[-300,1250]" />
  <nodo name_node="dwf_right_torso_missile10_mh2" schematic_pos="[-400,1250]" />
  <nodo name_node="dwf_right_torso_missile12_mh2" schematic_pos="[-500,1250]" />  
  <nodo name_node="dwf_right_torso_missile15_mh2" schematic_pos="[-600,1250]" />
  <nodo name_node="dwf_right_torso_missile20_mh2" schematic_pos="[-700,1250]" />
  <nodo name_node="dwf_right_torso_rl10_mh2" schematic_pos="[-900,1250]" />  
  <nodo name_node="dwf_right_torso_rl15_mh2" schematic_pos="[-1000,1250]" />    
  <nodo name_node="dwf_right_torso_rl20_mh2" schematic_pos="[-1100,1250]" />   
  <nodo name_node="dwf_right_torso_narc_mh3" schematic_pos="[300,1740]" />
  <nodo name_node="dwf_right_torso_missile2_mh3" schematic_pos="[200,1740]" />
  <nodo name_node="dwf_right_torso_missile3_mh3" schematic_pos="[100,1740]" />
  <nodo name_node="dwf_right_torso_missile4_mh3" schematic_pos="[000,1740]" />
  <nodo name_node="dwf_right_torso_missile5_mh3" schematic_pos="[-100,1740]" />
  <nodo name_node="dwf_right_torso_missile6_mh3" schematic_pos="[-200,1740]" />
  <nodo name_node="dwf_right_torso_missile9_mh3" schematic_pos="[-300,1740]" />
  <nodo name_node="dwf_right_torso_missile10_mh3" schematic_pos="[-400,1740]" />
  <nodo name_node="dwf_right_torso_missile12_mh3" schematic_pos="[-500,1740]" />  
  <nodo name_node="dwf_right_torso_missile15_mh3" schematic_pos="[-600,1740]" />
  <nodo name_node="dwf_right_torso_missile20_mh3" schematic_pos="[-700,1740]" />
  <nodo name_node="dwf_right_torso_rl10_mh3" schematic_pos="[-900,1740]" />  
  <nodo name_node="dwf_right_torso_rl15_mh3" schematic_pos="[-1000,1740]" />    
  <nodo name_node="dwf_right_torso_rl20_mh3" schematic_pos="[-1100,1740]" />   
  <nodo name_node="dwf_right_torso_narc_mh4" schematic_pos="[300,-1370]" />
  <nodo name_node="dwf_right_torso_missile2_mh4" schematic_pos="[200,-1370]" />
  <nodo name_node="dwf_right_torso_missile3_mh4" schematic_pos="[100,-1370]" />
  <nodo name_node="dwf_right_torso_missile4_mh4" schematic_pos="[000,-1370]" />
  <nodo name_node="dwf_right_torso_missile5_mh4" schematic_pos="[-100,-1370]" />
  <nodo name_node="dwf_right_torso_missile6_mh4" schematic_pos="[-200,-1370]" />
  <nodo name_node="dwf_right_torso_missile9_mh4" schematic_pos="[-300,-1370]" />
  <nodo name_node="dwf_right_torso_missile10_mh4" schematic_pos="[-400,-1370]" />
  <nodo name_node="dwf_right_torso_missile12_mh4" schematic_pos="[-500,-1370]" />  
  <nodo name_node="dwf_right_torso_missile15_mh4" schematic_pos="[-600,-1370]" />
  <nodo name_node="dwf_right_torso_missile20_mh4" schematic_pos="[-700,-1370]" />
  <nodo name_node="dwf_right_torso_rl10_mh4" schematic_pos="[-900,-1370]" />  
  <nodo name_node="dwf_right_torso_rl15_mh4" schematic_pos="[-1000,-1370]" />    
  <nodo name_node="dwf_right_torso_rl20_mh4" schematic_pos="[-1100,-1370]" />  
  <nodo name_node="dwf_right_torso_narc_mh5" schematic_pos="[300,-1860]" />
  <nodo name_node="dwf_right_torso_missile2_mh5" schematic_pos="[200,-1860]" />
  <nodo name_node="dwf_right_torso_missile3_mh5" schematic_pos="[100,-1860]" />
  <nodo name_node="dwf_right_torso_missile4_mh5" schematic_pos="[000,-1860]" />
  <nodo name_node="dwf_right_torso_missile5_mh5" schematic_pos="[-100,-1860]" />
  <nodo name_node="dwf_right_torso_missile6_mh5" schematic_pos="[-200,-1860]" />
  <nodo name_node="dwf_right_torso_missile9_mh5" schematic_pos="[-300,-1860]" />
  <nodo name_node="dwf_right_torso_missile10_mh5" schematic_pos="[-400,-1860]" />
  <nodo name_node="dwf_right_torso_missile12_mh5" schematic_pos="[-500,-1860]" />  
  <nodo name_node="dwf_right_torso_missile15_mh5" schematic_pos="[-600,-1860]" />
  <nodo name_node="dwf_right_torso_missile20_mh5" schematic_pos="[-700,-1860]" />
  <nodo name_node="dwf_right_torso_rl10_mh5" schematic_pos="[-900,-1860]" />  
  <nodo name_node="dwf_right_torso_rl15_mh5" schematic_pos="[-1000,-1860]" />    
  <nodo name_node="dwf_right_torso_rl20_mh5" schematic_pos="[-1100,-1860]" />  
  
  

  <nodo name_node="dwf_right_arm_forearm_ams_ah1" schematic_pos="[-1800,000]" />
  <nodo name_node="dwf_right_arm_forearm_lams_ah1" schematic_pos="[-1900,000]" />
  <nodo name_node="dwf_right_arm_forearm_ams_ah2" schematic_pos="[-1800,-150]" />
  <nodo name_node="dwf_right_arm_forearm_lams_ah2" schematic_pos="[-1900,-150]" />    

  <nodo name_node="dwf_right_arm_forearm_hppc_eh1" schematic_pos="[-2300,150]" />
  <nodo name_node="dwf_right_arm_forearm_ppc_eh1" schematic_pos="[-2200,150]" />  
  <nodo name_node="dwf_right_arm_forearm_snppc_eh1" schematic_pos="[-2100,150]" />
  <nodo name_node="dwf_right_arm_forearm_lppc_eh1" schematic_pos="[-2000,150]" />
  <nodo name_node="dwf_right_arm_forearm_laser_eh1" schematic_pos="[-1900,150]" />
  <nodo name_node="dwf_right_arm_forearm_flamer_eh1" schematic_pos="[-1800,150]" />
  <nodo name_node="dwf_right_arm_forearm_hppc_eh2" schematic_pos="[-2300,280]" />
  <nodo name_node="dwf_right_arm_forearm_ppc_eh2" schematic_pos="[-2200,280]" />  
  <nodo name_node="dwf_right_arm_forearm_snppc_eh2" schematic_pos="[-2100,280]" />
  <nodo name_node="dwf_right_arm_forearm_lppc_eh2" schematic_pos="[-2000,280]" />
  <nodo name_node="dwf_right_arm_forearm_laser_eh2" schematic_pos="[-1900,280]" />
  <nodo name_node="dwf_right_arm_forearm_flamer_eh2" schematic_pos="[-1800,280]" />
  <nodo name_node="dwf_right_arm_forearm_hppc_eh3" schematic_pos="[-2300,-280]" />
  <nodo name_node="dwf_right_arm_forearm_ppc_eh3" schematic_pos="[-2200,-280]" />  
  <nodo name_node="dwf_right_arm_forearm_snppc_eh3" schematic_pos="[-2100,-280]" />
  <nodo name_node="dwf_right_arm_forearm_lppc_eh3" schematic_pos="[-2-150,-280]" />
  <nodo name_node="dwf_right_arm_forearm_laser_eh3" schematic_pos="[-1900,-280]" />
  <nodo name_node="dwf_right_arm_forearm_flamer_eh3" schematic_pos="[-1800,-280]" />
  <nodo name_node="dwf_right_arm_forearm_hppc_eh4" schematic_pos="[-2300,-410]" />
  <nodo name_node="dwf_right_arm_forearm_ppc_eh4" schematic_pos="[-2200,-410]" />  
  <nodo name_node="dwf_right_arm_forearm_snppc_eh4" schematic_pos="[-2100,-410]" />
  <nodo name_node="dwf_right_arm_forearm_lppc_eh4" schematic_pos="[-2-150,-410]" />
  <nodo name_node="dwf_right_arm_forearm_laser_eh4" schematic_pos="[-1900,-410]" />
  <nodo name_node="dwf_right_arm_forearm_flamer_eh4" schematic_pos="[-1800,-410]" />
  <nodo name_node="dwf_right_arm_forearm_hppc_eh5" schematic_pos="[-2300,-540]" />
  <nodo name_node="dwf_right_arm_forearm_ppc_eh5" schematic_pos="[-2200,-540]" />  
  <nodo name_node="dwf_right_arm_forearm_snppc_eh5" schematic_pos="[-2100,-540]" />
  <nodo name_node="dwf_right_arm_forearm_lppc_eh5" schematic_pos="[-2000,-540]" />
  <nodo name_node="dwf_right_arm_forearm_laser_eh5" schematic_pos="[-1900,-540]" />
  <nodo name_node="dwf_right_arm_forearm_flamer_eh5" schematic_pos="[-1800,-540]" />  

  <nodo name_node="dwf_right_arm_forearm_lmg_bh1" schematic_pos="[-1800,420]" />
  <nodo name_node="dwf_right_arm_forearm_mg_bh1" schematic_pos="[-1900,420]" />
  <nodo name_node="dwf_right_arm_forearm_hmg_bh1" schematic_pos="[-2000,420]" />
  <nodo name_node="dwf_right_arm_forearm_ac2_bh1" schematic_pos="[-2100,420]" />
  <nodo name_node="dwf_right_arm_forearm_uac2_bh1" schematic_pos="[-2200,420]" />  
  <nodo name_node="dwf_right_arm_forearm_rac2_bh1" schematic_pos="[-2300,420]" />
  <nodo name_node="dwf_right_arm_forearm_lbx2_bh1" schematic_pos="[-2400,420]" />  
  <nodo name_node="dwf_right_arm_forearm_ac5_bh1" schematic_pos="[-2500,420]" />
  <nodo name_node="dwf_right_arm_forearm_lbx5_bh1" schematic_pos="[-2600,420]" />
  <nodo name_node="dwf_right_arm_forearm_uac5_bh1" schematic_pos="[-2700,420]" />
  <nodo name_node="dwf_right_arm_forearm_lgauss_bh1" schematic_pos="[-2800,420]" />
  <nodo name_node="dwf_right_arm_forearm_rac5_bh1" schematic_pos="[-2900,420]" />
  <nodo name_node="dwf_right_arm_forearm_lbx10_bh1" schematic_pos="[-3000,420]" />
  <nodo name_node="dwf_right_arm_forearm_ac10_bh1" schematic_pos="[-3100,420]" />
  <nodo name_node="dwf_right_arm_forearm_uac10_bh1" schematic_pos="[-3200,420]" />
  <nodo name_node="dwf_right_arm_forearm_gauss_bh1" schematic_pos="[-3300,420]" />
  <nodo name_node="dwf_right_arm_forearm_ac20_bh1" schematic_pos="[-3400,420]" />
  <nodo name_node="dwf_right_arm_forearm_uac20_bh1" schematic_pos="[-3500,420]" />
  <nodo name_node="dwf_right_arm_forearm_lbx20_bh1" schematic_pos="[-3600,420]" />
  <nodo name_node="dwf_right_arm_forearm_hgauss_bh1" schematic_pos="[-3700,420]" />
  <nodo name_node="dwf_right_arm_forearm_lmg_bh2" schematic_pos="[-1800,590]" />
  <nodo name_node="dwf_right_arm_forearm_mg_bh2" schematic_pos="[-1900,590]" />
  <nodo name_node="dwf_right_arm_forearm_hmg_bh2" schematic_pos="[-2000,590]" />
  <nodo name_node="dwf_right_arm_forearm_ac2_bh2" schematic_pos="[-2100,590]" />
  <nodo name_node="dwf_right_arm_forearm_uac2_bh2" schematic_pos="[-2200,590]" />  
  <nodo name_node="dwf_right_arm_forearm_rac2_bh2" schematic_pos="[-2300,590]" />
  <nodo name_node="dwf_right_arm_forearm_lbx2_bh2" schematic_pos="[-2400,590]" />  
  <nodo name_node="dwf_right_arm_forearm_ac5_bh2" schematic_pos="[-2500,590]" />
  <nodo name_node="dwf_right_arm_forearm_lbx5_bh2" schematic_pos="[-2600,590]" />
  <nodo name_node="dwf_right_arm_forearm_uac5_bh2" schematic_pos="[-2700,590]" />
  <nodo name_node="dwf_right_arm_forearm_lgauss_bh2" schematic_pos="[-2800,590]" />
  <nodo name_node="dwf_right_arm_forearm_rac5_bh2" schematic_pos="[-2900,590]" />
  <nodo name_node="dwf_right_arm_forearm_lbx10_bh2" schematic_pos="[-3000,590]" />
  <nodo name_node="dwf_right_arm_forearm_ac10_bh2" schematic_pos="[-3100,590]" />
  <nodo name_node="dwf_right_arm_forearm_uac10_bh2" schematic_pos="[-3200,590]" />
  <nodo name_node="dwf_right_arm_forearm_gauss_bh2" schematic_pos="[-3300,590]" />
  <nodo name_node="dwf_right_arm_forearm_ac20_bh2" schematic_pos="[-3400,590]" />
  <nodo name_node="dwf_right_arm_forearm_uac20_bh2" schematic_pos="[-3500,590]" />
  <nodo name_node="dwf_right_arm_forearm_lbx20_bh2" schematic_pos="[-3600,590]" />
  <nodo name_node="dwf_right_arm_forearm_hgauss_bh2" schematic_pos="[-3700,590]" />
  <nodo name_node="dwf_right_arm_forearm_lmg_bh3" schematic_pos="[-1800,-710]" />
  <nodo name_node="dwf_right_arm_forearm_mg_bh3" schematic_pos="[-1900,-710]" />
  <nodo name_node="dwf_right_arm_forearm_hmg_bh3" schematic_pos="[-2-150,-710]" />
  <nodo name_node="dwf_right_arm_forearm_ac2_bh3" schematic_pos="[-2100,-710]" />
  <nodo name_node="dwf_right_arm_forearm_uac2_bh3" schematic_pos="[-2200,-710]" />  
  <nodo name_node="dwf_right_arm_forearm_rac2_bh3" schematic_pos="[-2300,-710]" />
  <nodo name_node="dwf_right_arm_forearm_lbx2_bh3" schematic_pos="[-2400,-710]" />  
  <nodo name_node="dwf_right_arm_forearm_ac5_bh3" schematic_pos="[-2500,-710]" />
  <nodo name_node="dwf_right_arm_forearm_lbx5_bh3" schematic_pos="[-2600,-710]" />
  <nodo name_node="dwf_right_arm_forearm_uac5_bh3" schematic_pos="[-2700,-710]" />
  <nodo name_node="dwf_right_arm_forearm_lgauss_bh3" schematic_pos="[-2800,-710]" />
  <nodo name_node="dwf_right_arm_forearm_rac5_bh3" schematic_pos="[-2900,-710]" />
  <nodo name_node="dwf_right_arm_forearm_lbx10_bh3" schematic_pos="[-3-150,-710]" />
  <nodo name_node="dwf_right_arm_forearm_ac10_bh3" schematic_pos="[-3100,-710]" />
  <nodo name_node="dwf_right_arm_forearm_uac10_bh3" schematic_pos="[-3200,-710]" />
  <nodo name_node="dwf_right_arm_forearm_gauss_bh3" schematic_pos="[-3300,-710]" />
  <nodo name_node="dwf_right_arm_forearm_ac20_bh3" schematic_pos="[-3400,-710]" />
  <nodo name_node="dwf_right_arm_forearm_uac20_bh3" schematic_pos="[-3500,-710]" />
  <nodo name_node="dwf_right_arm_forearm_lbx20_bh3" schematic_pos="[-3600,-710]" />
  <nodo name_node="dwf_right_arm_forearm_hgauss_bh3" schematic_pos="[-3700,-710]" />
  <nodo name_node="dwf_right_arm_forearm_lmg_bh4" schematic_pos="[-1800,-880]" />
  <nodo name_node="dwf_right_arm_forearm_mg_bh4" schematic_pos="[-1900,-880]" />
  <nodo name_node="dwf_right_arm_forearm_hmg_bh4" schematic_pos="[-2-150,-880]" />
  <nodo name_node="dwf_right_arm_forearm_ac2_bh4" schematic_pos="[-2100,-880]" />
  <nodo name_node="dwf_right_arm_forearm_uac2_bh4" schematic_pos="[-2200,-880]" />  
  <nodo name_node="dwf_right_arm_forearm_rac2_bh4" schematic_pos="[-2300,-880]" />
  <nodo name_node="dwf_right_arm_forearm_lbx2_bh4" schematic_pos="[-2400,-880]" />  
  <nodo name_node="dwf_right_arm_forearm_ac5_bh4" schematic_pos="[-2500,-880]" />
  <nodo name_node="dwf_right_arm_forearm_lbx5_bh4" schematic_pos="[-2600,-880]" />
  <nodo name_node="dwf_right_arm_forearm_uac5_bh4" schematic_pos="[-2700,-880]" />
  <nodo name_node="dwf_right_arm_forearm_lgauss_bh4" schematic_pos="[-2800,-880]" />
  <nodo name_node="dwf_right_arm_forearm_rac5_bh4" schematic_pos="[-2900,-880]" />
  <nodo name_node="dwf_right_arm_forearm_lbx10_bh4" schematic_pos="[-3-150,-880]" />
  <nodo name_node="dwf_right_arm_forearm_ac10_bh4" schematic_pos="[-3100,-880]" />
  <nodo name_node="dwf_right_arm_forearm_uac10_bh4" schematic_pos="[-3200,-880]" />
  <nodo name_node="dwf_right_arm_forearm_gauss_bh4" schematic_pos="[-3300,-880]" />
  <nodo name_node="dwf_right_arm_forearm_ac20_bh4" schematic_pos="[-3400,-880]" />
  <nodo name_node="dwf_right_arm_forearm_uac20_bh4" schematic_pos="[-3500,-880]" />
  <nodo name_node="dwf_right_arm_forearm_lbx20_bh4" schematic_pos="[-3600,-880]" />
  <nodo name_node="dwf_right_arm_forearm_hgauss_bh4" schematic_pos="[-3700,-880]" />
  
  <nodo name_node="dwf_right_arm_forearm_narc_mh1" schematic_pos="[-1800,760]" />
  <nodo name_node="dwf_right_arm_forearm_missile2_mh1" schematic_pos="[-1900,760]" />
  <nodo name_node="dwf_right_arm_forearm_missile3_mh1" schematic_pos="[-2000,760]" />
  <nodo name_node="dwf_right_arm_forearm_missile4_mh1" schematic_pos="[-2100,760]" />
  <nodo name_node="dwf_right_arm_forearm_missile5_mh1" schematic_pos="[-2200,760]" />
  <nodo name_node="dwf_right_arm_forearm_missile6_mh1" schematic_pos="[-2300,760]" />
  <nodo name_node="dwf_right_arm_forearm_missile9_mh1" schematic_pos="[-2400,760]" />
  <nodo name_node="dwf_right_arm_forearm_missile10_mh1" schematic_pos="[-2500,760]" />
  <nodo name_node="dwf_right_arm_forearm_missile12_mh1" schematic_pos="[-2600,760]" />  
  <nodo name_node="dwf_right_arm_forearm_missile15_mh1" schematic_pos="[-2700,760]" />
  <nodo name_node="dwf_right_arm_forearm_missile20_mh1" schematic_pos="[-2800,760]" />
  <nodo name_node="dwf_right_arm_forearm_rl10_mh1" schematic_pos="[-3000,760]" />  
  <nodo name_node="dwf_right_arm_forearm_rl15_mh1" schematic_pos="[-3100,760]" />    
  <nodo name_node="dwf_right_arm_forearm_rl20_mh1" schematic_pos="[-3200,760]" />  
  <nodo name_node="dwf_right_arm_forearm_narc_mh2" schematic_pos="[-1800,1250]" />
  <nodo name_node="dwf_right_arm_forearm_missile2_mh2" schematic_pos="[-1900,1250]" />
  <nodo name_node="dwf_right_arm_forearm_missile3_mh2" schematic_pos="[-2000,1250]" />
  <nodo name_node="dwf_right_arm_forearm_missile4_mh2" schematic_pos="[-2100,1250]" />
  <nodo name_node="dwf_right_arm_forearm_missile5_mh2" schematic_pos="[-2200,1250]" />
  <nodo name_node="dwf_right_arm_forearm_missile6_mh2" schematic_pos="[-2300,1250]" />
  <nodo name_node="dwf_right_arm_forearm_missile9_mh2" schematic_pos="[-2400,1250]" />
  <nodo name_node="dwf_right_arm_forearm_missile10_mh2" schematic_pos="[-2500,1250]" />
  <nodo name_node="dwf_right_arm_forearm_missile12_mh2" schematic_pos="[-2600,1250]" />  
  <nodo name_node="dwf_right_arm_forearm_missile15_mh2" schematic_pos="[-2700,1250]" />
  <nodo name_node="dwf_right_arm_forearm_missile20_mh2" schematic_pos="[-2800,1250]" />
  <nodo name_node="dwf_right_arm_forearm_rl10_mh2" schematic_pos="[-3000,1250]" />  
  <nodo name_node="dwf_right_arm_forearm_rl15_mh2" schematic_pos="[-3100,1250]" />    
  <nodo name_node="dwf_right_arm_forearm_rl20_mh2" schematic_pos="[-3200,1250]" />  
  <nodo name_node="dwf_right_arm_forearm_narc_mh3" schematic_pos="[-1800,1740]" />
  <nodo name_node="dwf_right_arm_forearm_missile2_mh3" schematic_pos="[-1900,1740]" />
  <nodo name_node="dwf_right_arm_forearm_missile3_mh3" schematic_pos="[-2000,1740]" />
  <nodo name_node="dwf_right_arm_forearm_missile4_mh3" schematic_pos="[-2100,1740]" />
  <nodo name_node="dwf_right_arm_forearm_missile5_mh3" schematic_pos="[-2200,1740]" />
  <nodo name_node="dwf_right_arm_forearm_missile6_mh3" schematic_pos="[-2300,1740]" />
  <nodo name_node="dwf_right_arm_forearm_missile9_mh3" schematic_pos="[-2400,1740]" />
  <nodo name_node="dwf_right_arm_forearm_missile10_mh3" schematic_pos="[-2500,1740]" />
  <nodo name_node="dwf_right_arm_forearm_missile12_mh3" schematic_pos="[-2600,1740]" />  
  <nodo name_node="dwf_right_arm_forearm_missile15_mh3" schematic_pos="[-2700,1740]" />
  <nodo name_node="dwf_right_arm_forearm_missile20_mh3" schematic_pos="[-2800,1740]" />
  <nodo name_node="dwf_right_arm_forearm_rl10_mh3" schematic_pos="[-3000,1740]" />  
  <nodo name_node="dwf_right_arm_forearm_rl15_mh3" schematic_pos="[-3100,1740]" />    
  <nodo name_node="dwf_right_arm_forearm_rl20_mh3" schematic_pos="[-3200,1740]" />
  <nodo name_node="dwf_right_arm_forearm_narc_mh4" schematic_pos="[-1800,-1370]" />
  <nodo name_node="dwf_right_arm_forearm_missile2_mh4" schematic_pos="[-1900,-1370]" />
  <nodo name_node="dwf_right_arm_forearm_missile3_mh4" schematic_pos="[-2-150,-1370]" />
  <nodo name_node="dwf_right_arm_forearm_missile4_mh4" schematic_pos="[-2100,-1370]" />
  <nodo name_node="dwf_right_arm_forearm_missile5_mh4" schematic_pos="[-2200,-1370]" />
  <nodo name_node="dwf_right_arm_forearm_missile6_mh4" schematic_pos="[-2300,-1370]" />
  <nodo name_node="dwf_right_arm_forearm_missile9_mh4" schematic_pos="[-2400,-1370]" />
  <nodo name_node="dwf_right_arm_forearm_missile10_mh4" schematic_pos="[-2500,-1370]" />
  <nodo name_node="dwf_right_arm_forearm_missile12_mh4" schematic_pos="[-2600,-1370]" />  
  <nodo name_node="dwf_right_arm_forearm_missile15_mh4" schematic_pos="[-2700,-1370]" />
  <nodo name_node="dwf_right_arm_forearm_missile20_mh4" schematic_pos="[-2800,-1370]" />
  <nodo name_node="dwf_right_arm_forearm_rl10_mh4" schematic_pos="[-3-150,-1370]" />  
  <nodo name_node="dwf_right_arm_forearm_rl15_mh4" schematic_pos="[-3100,-1370]" />    
  <nodo name_node="dwf_right_arm_forearm_rl20_mh4" schematic_pos="[-3200,-1370]" />  
  <nodo name_node="dwf_right_arm_forearm_narc_mh5" schematic_pos="[-1800,-1860]" />
  <nodo name_node="dwf_right_arm_forearm_missile2_mh5" schematic_pos="[-1900,-1860]" />
  <nodo name_node="dwf_right_arm_forearm_missile3_mh5" schematic_pos="[-2-150,-1860]" />
  <nodo name_node="dwf_right_arm_forearm_missile4_mh5" schematic_pos="[-2100,-1860]" />
  <nodo name_node="dwf_right_arm_forearm_missile5_mh5" schematic_pos="[-2200,-1860]" />
  <nodo name_node="dwf_right_arm_forearm_missile6_mh5" schematic_pos="[-2300,-1860]" />
  <nodo name_node="dwf_right_arm_forearm_missile9_mh5" schematic_pos="[-2400,-1860]" />
  <nodo name_node="dwf_right_arm_forearm_missile10_mh5" schematic_pos="[-2500,-1860]" />
  <nodo name_node="dwf_right_arm_forearm_missile12_mh5" schematic_pos="[-2600,-1860]" />  
  <nodo name_node="dwf_right_arm_forearm_missile15_mh5" schematic_pos="[-2700,-1860]" />
  <nodo name_node="dwf_right_arm_forearm_missile20_mh5" schematic_pos="[-2800,-1860]" />
  <nodo name_node="dwf_right_arm_forearm_rl10_mh5" schematic_pos="[-3-150,-1860]" />  
  <nodo name_node="dwf_right_arm_forearm_rl15_mh5" schematic_pos="[-3100,-1860]" />    
  <nodo name_node="dwf_right_arm_forearm_rl20_mh5" schematic_pos="[-3200,-1860]" /> 

  <nodo name_node="dwf_right_arm_forearm_blank_mh1" schematic_pos="[-1670,250]" />
</Root>                                                 